{
  "name": "sudc-system",
  "namespace": "sudc",
  "id": "62999e58-66a0-4e50-a870-f2673acf6c79",
  "containerDefinitions": [
    {
      "type": "blank-container",
      "id": "machine",
      "name": "machine"
    },
    {
      "type": "blank-container",
      "id": "root",
      "name": "root"
    },
    {
      "type": "docker",
      "specific": {
        "repositoryUrl": "git@github.com:nearform/sudc-doc.git",
        "buildScript": "build.sh",
        "execute": {
          "args": "-p 9002:9002 -d",
          "exec": "/usr/bin/node /srv/doc-srv.js"
        },
        "buildHead": 4,
        "binary": "/Users/pelger/work/nearform/code/product/nscale/examples/sudc/sudc-system/builds/doc-3",
        "dockerImageId": "19279ac8130e9148bce4ac406e59eec215fa0cee5d4aa88299510c51c7f3269c"
      },
      "id": "doc",
      "name": "doc"
    },
    {
      "type": "docker",
      "specific": {
        "repositoryUrl": "git@github.com:nearform/sudc-history.git",
        "buildScript": "build.sh",
        "execute": {
          "args": "-p 9003:9003 -d",
          "exec": "/usr/bin/node /srv/hist-srv.js"
        },
        "buildHead": 2,
        "binary": "/Users/pelger/work/nearform/code/product/nscale/examples/sudc/sudc-system/builds/hist-1",
        "dockerImageId": "ffd8a6a135bdf9f8b3f783be61f1b29f54391af9e53295aa194a21abfc29c419"
      },
      "id": "hist",
      "name": "hist"
    },
    {
      "type": "docker",
      "specific": {
        "repositoryUrl": "git@github.com:nearform/sudc-realtime.git",
        "buildScript": "build.sh",
        "execute": {
          "args": "-p 9001:9001 -d",
          "exec": "/usr/bin/node /srv/real-srv.js"
        },
        "buildHead": 3,
        "binary": "/Users/pelger/work/nearform/code/product/nscale/examples/sudc/sudc-system/builds/real-2",
        "dockerImageId": "3d8943bbd715b253d288d3da06fa98cc1d2582fa9064fbd63455c7aa31f71472"
      },
      "id": "real",
      "name": "real"
    },
    {
      "type": "docker",
      "specific": {
        "repositoryUrl": "git@github.com:nearform/sudc-web.git",
        "buildScript": "build.sh",
        "execute": {
          "args": "-p 8000:8000 -d",
          "exec": "/bin/bash /web/run.sh"
        },
        "buildHead": 2,
        "binary": "/Users/pelger/work/nearform/code/product/nscale/examples/sudc/sudc-system/builds/web-1",
        "dockerImageId": "493cd7b5579ee54dbfa5a50364add2d0b11532c0a1ab7870f23b2d10e967f2b0"
      },
      "id": "web",
      "name": "web"
    }
  ],
  "topology": {
    "containers": {
      "machine$123-8d591e7a": {
        "id": "machine$123-8d591e7a",
        "containedBy": "machine$123-8d591e7a",
        "containerDefinitionId": "machine$123",
        "contains": [
          "doc-754403b9",
          "hist-243332f",
          "real-9b4a6295",
          "web-ec4d5203"
        ],
        "specific": {
          "user": "root",
          "identityFile": "sudc-key"
        }
      },
      "doc-754403b9": {
        "id": "doc-754403b9",
        "containedBy": "machine$123-8d591e7a",
        "containerDefinitionId": "doc",
        "type": "docker",
        "contains": [],
        "specific": {
          "repositoryUrl": "git@github.com:nearform/sudc-doc.git",
          "buildScript": "build.sh",
          "execute": {
            "args": "-p 9002:9002 -d",
            "exec": "/usr/bin/node /srv/doc-srv.js"
          },
          "dockerImageId": "19279ac8130e9148bce4ac406e59eec215fa0cee5d4aa88299510c51c7f3269c",
          "containerBinary": "/Users/pelger/work/nearform/code/product/nscale/examples/sudc/sudc-system/builds/doc-3",
          "dockerLocalTag": "sudc/doc-3",
          "buildNumber": 3,
          "version": "0.0.0"
        }
      },
      "hist-243332f": {
        "id": "hist-243332f",
        "containedBy": "machine$123-8d591e7a",
        "containerDefinitionId": "hist",
        "type": "docker",
        "contains": [],
        "specific": {
          "repositoryUrl": "git@github.com:nearform/sudc-history.git",
          "buildScript": "build.sh",
          "execute": {
            "args": "-p 9003:9003 -d",
            "exec": "/usr/bin/node /srv/hist-srv.js"
          },
          "dockerImageId": "ffd8a6a135bdf9f8b3f783be61f1b29f54391af9e53295aa194a21abfc29c419",
          "containerBinary": "/Users/pelger/work/nearform/code/product/nscale/examples/sudc/sudc-system/builds/hist-1",
          "dockerLocalTag": "sudc/hist-1",
          "buildNumber": 1,
          "version": "0.0.0"
        }
      },
      "real-9b4a6295": {
        "id": "real-9b4a6295",
        "containedBy": "machine$123-8d591e7a",
        "containerDefinitionId": "real",
        "type": "docker",
        "contains": [],
        "specific": {
          "repositoryUrl": "git@github.com:nearform/sudc-realtime.git",
          "buildScript": "build.sh",
          "execute": {
            "args": "-p 9001:9001 -d",
            "exec": "/usr/bin/node /srv/real-srv.js"
          },
          "dockerImageId": "3d8943bbd715b253d288d3da06fa98cc1d2582fa9064fbd63455c7aa31f71472",
          "containerBinary": "/Users/pelger/work/nearform/code/product/nscale/examples/sudc/sudc-system/builds/real-2",
          "dockerLocalTag": "sudc/real-2",
          "buildNumber": 2,
          "version": "0.0.0"
        }
      },
      "web-ec4d5203": {
        "id": "web-ec4d5203",
        "containedBy": "machine$123-8d591e7a",
        "containerDefinitionId": "web",
        "type": "docker",
        "contains": [],
        "specific": {
          "repositoryUrl": "git@github.com:nearform/sudc-web.git",
          "buildScript": "build.sh",
          "execute": {
            "args": "-p 8000:8000 -d",
            "exec": "/bin/bash /web/run.sh"
          },
          "dockerImageId": "493cd7b5579ee54dbfa5a50364add2d0b11532c0a1ab7870f23b2d10e967f2b0",
          "containerBinary": "/Users/pelger/work/nearform/code/product/nscale/examples/sudc/sudc-system/builds/web-1",
          "dockerLocalTag": "sudc/web-1",
          "buildNumber": 1,
          "version": "0.0.0"
        }
      },
      "root-bbff7e65": {
        "id": "root-bbff7e65",
        "containedBy": "user-bbff7e65",
        "containerDefinitionId": "root",
        "type": "blank-container",
        "contains": [],
        "specific": {}
      }
    }
  }
}